mirapolis_virtualroom/__init__.py
mirapolis_virtualroom/base_api.py
mirapolis_virtualroom/models.py
mirapolis_virtualroom/virtualroom_api.py
mirapolis_virtualroom-0.2.9.dist-info/LICENSE
mirapolis_virtualroom-0.2.9.dist-info/METADATA
mirapolis_virtualroom-0.2.9.dist-info/WHEEL
mirapolis_virtualroom-0.2.9.dist-info/RECORD
