Metadata-Version: 2.1
Name: mirapolis-virtualroom
Version: 0.2.9
Summary: Python API Client for Mirapolis VirtualRoom. Based on original documentation. Uses Pydantic and aiohttp.
Home-page: https://github.com/gulyaeve/mirapolis_virtualroom
License: MIT
Keywords: mirapolis,virtualroom
Author: gulyaeve
Author-email: gulyaev.e@icloud.com
Requires-Python: >=3.12,<4.0
Classifier: License :: OSI Approved :: MIT License
Classifier: Operating System :: OS Independent
Classifier: Programming Language :: Python :: 3
Classifier: Programming Language :: Python :: 3.12
Requires-Dist: aiohttp (>=3.9.3,<4.0.0)
Requires-Dist: pydantic (>=2.6.4,<3.0.0)
Project-URL: Repository, https://github.com/gulyaeve/mirapolis_virtualroom
